core/__init__.py
core/database.py
core/exceptions.py
core/log.py
core/message.py
core/mqtt.py
core/time.py
core/utils.py
core/weatherData.py
policumbent_bob_core-0.3.3.dist-info/LICENSE
policumbent_bob_core-0.3.3.dist-info/WHEEL
policumbent_bob_core-0.3.3.dist-info/METADATA
policumbent_bob_core-0.3.3.dist-info/RECORD
