Metadata-Version: 2.1
Name: policumbent-bob-core
Version: 0.3.3
Summary: BOB common files
License: LGPL-3.0-or-later
Author: Gabriele Belluardo
Author-email: gabriele.belluardo@outlook.it
Requires-Python: >=3.7.3,<4.0.0
Classifier: License :: OSI Approved :: GNU Lesser General Public License v3 or later (LGPLv3+)
Classifier: Programming Language :: Python :: 3
Classifier: Programming Language :: Python :: 3.10
Classifier: Programming Language :: Python :: 3.8
Classifier: Programming Language :: Python :: 3.9
Requires-Dist: asyncio-mqtt (>=0.12.1,<0.13.0)
Requires-Dist: colorama (>=0.4.4,<0.5.0)
